pyapiRenat0000/JSONReader.py
pyapiRenat0000/__init__.py
pyapirenat0000-1.0.5.dist-info/licenses/LICENSE
pyapirenat0000-1.0.5.dist-info/METADATA
pyapirenat0000-1.0.5.dist-info/WHEEL
pyapirenat0000-1.0.5.dist-info/top_level.txt
pyapirenat0000-1.0.5.dist-info/RECORD
