Metadata-Version: 2.4
Name: pyapiRenat0000
Version: 1.0.5
Summary: A Python API(unofficial)
Author-email: Renat0000 <road10mc@gmail.com>
License: This project is free to distribute and you can use this project in your projects.
Classifier: Programming Language :: Python :: 3
Classifier: Operating System :: OS Independent
Requires-Python: >=3.9
License-File: LICENSE
Dynamic: license-file
